seedftw/__init__.py
seedftw/_version.py
seedftw/exceptions.py
seedftw/base/__init__.py
seedftw/base/timeseries.py
seedftw/base/tricks.py
seedftw/base/types.py
seedftw/energy/__init__.py
seedftw/energy/denmark.py
seedftw/energy/energy_asset.py
seedftw/energy/great_britain.py
seedftw/energy/network.py
seedftw/environment/__init__.py
seedftw/environment/denmark.py
seedftw/environment/geography.py
seedftw/environment/solar.py
seedftw/visual/__init__.py
seedftw/visual/figure.py
seedftw/visual/plot.py
seedftw-1.4.dist-info/LICENSE
seedftw-1.4.dist-info/METADATA
seedftw-1.4.dist-info/WHEEL
seedftw-1.4.dist-info/top_level.txt
seedftw-1.4.dist-info/RECORD
