Metadata-Version: 2.1
Name: seedftw
Version: 1.4
Summary: Simple Energy & Environment Data From The World (aka. seedftw) - A small example package for acquiring open energy and environment data
Home-page: https://gitlab.com/Pierre_VF/seedftw
Author: PVF
Author-email: pvf@dtime.ai
License: UNKNOWN
Platform: UNKNOWN
Classifier: Programming Language :: Python :: 3
Classifier: License :: OSI Approved :: MIT License
Classifier: Operating System :: OS Independent
Requires-Python: >=3.7
License-File: LICENSE
Requires-Dist: numpy
Requires-Dist: pandas
Requires-Dist: plotly
Requires-Dist: pytz
Requires-Dist: requests
Requires-Dist: setuptools
Requires-Dist: xlrd
Provides-Extra: all
Requires-Dist: plotly ; extra == 'all'
Requires-Dist: black ; extra == 'all'
Requires-Dist: pytest ; extra == 'all'
Requires-Dist: versioneer ; extra == 'all'
Requires-Dist: coverage ; extra == 'all'
Requires-Dist: build ; extra == 'all'
Provides-Extra: dev
Requires-Dist: black ; extra == 'dev'
Requires-Dist: pytest ; extra == 'dev'
Requires-Dist: versioneer ; extra == 'dev'
Requires-Dist: coverage ; extra == 'dev'
Requires-Dist: build ; extra == 'dev'
